aitoolman/__init__.py
aitoolman/__main__.py
aitoolman/app.py
aitoolman/channel.py
aitoolman/cli.py
aitoolman/client.py
aitoolman/model.py
aitoolman/module.py
aitoolman/postprocess.py
aitoolman/provider.py
aitoolman/resmanager.py
aitoolman/util.py
aitoolman/wsserver.py
aitoolman/zmqclient.py
aitoolman/zmqserver.py
aitoolman-0.1.1.dist-info/METADATA
aitoolman-0.1.1.dist-info/WHEEL
aitoolman-0.1.1.dist-info/licenses/LICENSE
aitoolman-0.1.1.dist-info/RECORD
