Metadata-Version: 2.4
Name: aitoolman
Version: 0.1.1
Summary: Controllable and Transparent LLM Application Framework
Project-URL: Homepage, https://github.com/gumblex/aitoolman
Project-URL: Issues, https://github.com/gumblex/aitoolman/issues
Author-email: Dingyuan Wang <abcdoyle888@gmail.com>
License-Expression: MIT
License-File: LICENSE
Classifier: Development Status :: 4 - Beta
Classifier: Intended Audience :: Developers
Classifier: License :: OSI Approved :: MIT License
Classifier: Operating System :: OS Independent
Classifier: Programming Language :: Python :: 3
Classifier: Topic :: Scientific/Engineering :: Artificial Intelligence
Classifier: Topic :: Software Development :: Libraries :: Application Frameworks
Requires-Python: >=3.8
Requires-Dist: beautifulsoup4
Requires-Dist: httpx-sse
Requires-Dist: httpx[http2]
Requires-Dist: jinja2
Requires-Dist: json-repair
Requires-Dist: lxml
Requires-Dist: pyzmq
Requires-Dist: xmltodict
Provides-Extra: all
Requires-Dist: pyzmq; extra == 'all'
Requires-Dist: uuid-utils; extra == 'all'
Requires-Dist: websockets; extra == 'all'
Provides-Extra: uuid
Requires-Dist: uuid-utils; extra == 'uuid'
Provides-Extra: ws
Requires-Dist: websockets; extra == 'ws'
